poetry_aws_sam/__init__.py
poetry_aws_sam/aws.py
poetry_aws_sam/export.py
poetry_aws_sam/plugin.py
poetry_aws_sam/sam.py
poetry_aws_sam-1.4.3.dist-info/METADATA
poetry_aws_sam-1.4.3.dist-info/WHEEL
poetry_aws_sam-1.4.3.dist-info/entry_points.txt
poetry_aws_sam-1.4.3.dist-info/RECORD
