Metadata-Version: 2.1
Name: poetry-aws-sam
Version: 1.4.3
Summary: Poetry plugin to work with AWS's SAM serverless tool
Home-page: https://github.com/upjohnc/poetry-aws-sam
License: MIT
Author: Chad Upjohn
Author-email: chad.upjohn@pinnsg.com
Requires-Python: >=3.10,<4.0
Classifier: License :: OSI Approved :: MIT License
Classifier: Programming Language :: Python :: 3
Classifier: Programming Language :: Python :: 3.10
Classifier: Programming Language :: Python :: 3.11
Classifier: Programming Language :: Python :: 3.12
Classifier: Programming Language :: Python :: 3.13
Requires-Dist: click (>=8.1.7,<9.0.0)
Requires-Dist: poetry (>=1.7.1,<2.0.0)
Requires-Dist: poetry-plugin-export (==1.6.*)
Requires-Dist: pyyaml (>=6.0.1,<7.0.0)
Project-URL: Repository, https://github.com/upjohnc/poetry-aws-sam
